{
  "funcionarios": [
    {
      "id": 1,
      "nome": "João",
      "sobrenome": "Silva",
      "departamento": "TI",
      "ativo": false,
      "turno": "Manha",
      "dataCriacao": "2021-08-01",
      "dataAtualizacao": "2021-08-01"
    },
    {
      "id": 2,
      "nome": "Maria",
      "sobrenome": "Santos",
      "departamento": "RH",
      "ativo": true,
      "turno": "Tarde",
      "dataCriacao": "2021-08-01",
      "dataAtualizacao": "2021-08-01"
    },
    {
      "id": 3,
      "nome": "Jose",
      "sobrenome": "Junior",
      "departamento": "Financeiro",
      "turno": "Tarde",
      "ativo": true,
      "dataCriacao": "2024-08-18T19:26:25.712Z",
      "dataAtualizacao": "2024-08-18T19:26:25.712Z"
    },
    {
      "id": 4,
      "nome": "Julia",
      "sobrenome": "Souza",
      "departamento": "Comercial",
      "turno": "Tarde",
      "ativo": true,
      "dataCriacao": "2024-08-18T20:48:39.970Z",
      "dataAtualizacao": "2024-08-18T20:48:39.970Z"
    }
  ]
}